{
  "version": 6,
  "cmakeMinimumRequired": {
    "major": 3,
    "minor": 25,
    "patch": 0
  },
  "configurePresets": [
    {
      "name": "windows-debug",
      "displayName": "Windows Debug",
      "description": "Debug build with Ninja",
      "generator": "Ninja",
      "binaryDir": "${sourceDir}/build/windows-debug",
      "cacheVariables": {
        "CMAKE_BUILD_TYPE": "Debug",
        "CMAKE_CXX_COMPILER": "cl",
        "CMAKE_C_COMPILER": "cl",
        "CMAKE_EXPORT_COMPILE_COMMANDS": "ON"
      }
    },
    {
      "name": "windows-release",
      "displayName": "Windows Release",
      "description": "Release build with Ninja",
      "generator": "Ninja",
      "binaryDir": "${sourceDir}/build/windows-release",
      "cacheVariables": {
        "CMAKE_BUILD_TYPE": "Release",
        "CMAKE_CXX_COMPILER": "cl",
        "CMAKE_C_COMPILER": "cl",
        "CMAKE_EXPORT_COMPILE_COMMANDS": "ON"
      }
    }
  ],
  "buildPresets": [
    {
      "name": "build-debug",
      "configurePreset": "windows-debug"
    },
    {
      "name": "build-release",
      "configurePreset": "windows-release"
    }
  ]
}